hivepy/__init__.py
hivepy/hive_api.py
hivepy/api_management/__init__.py
hivepy/api_management/enums.py
hivepy/api_management/mode_handler.py
hivepy/api_management/object_builder.py
hivepy/field_management/__init__.py
hivepy/field_management/enums.py
hivepy/field_management/json_field_normalizer.py
hivepy/field_management/builder/__init__.py
hivepy/field_management/builder/field_builder.py
hivepy/field_management/builder/field_model_builder.py
hivepy/field_management/models/__init__.py
hivepy/field_management/models/base_field.py
hivepy/field_management/models/fields.py
hivepy/issue_management/__init__.py
hivepy/issue_management/issue.py
hivepy/issue_management/issue_builder.py
hivepy/middleware/__init__.py
hivepy/middleware/hive_middleware.py
hivepy/project_management/__init__.py
hivepy/project_management/project.py
hivepy/project_management/project_builder.py
hivepy/rest/__init__.py
hivepy/rest/error_handler.py
hivepy/rest/exceptions.py
hivepy/rest/state.py
hivepy/rest/http_client/__init__.py
hivepy/rest/http_client/exceptions.py
hivepy/rest/http_client/http_client.py
hivepy/schema_management/__init__.py
hivepy/schema_management/builders/__init__.py
hivepy/schema_management/builders/issue_schema_builder.py
hivepy/schema_management/builders/project_schema_builder.py
hivepy/schema_management/builders/schema_builder.py
hivepy/schema_management/factories/__init__.py
hivepy/schema_management/factories/schema_factory.py
hivepy/schema_management/models/__init__.py
hivepy/schema_management/models/base_schema.py
hivepy/schema_management/models/issue_schema.py
hivepy/schema_management/models/project_schema.py
hivepy/template_management/__init__.py
hivepy/template_management/builders/__init__.py
hivepy/template_management/builders/issue_template_builder.py
hivepy/template_management/builders/project_template_builder.py
hivepy/template_management/builders/template_builder.py
hivepy/template_management/models/__init__.py
hivepy/template_management/models/base_template.py
hw_hivepy-0.3.1.dist-info/METADATA
hw_hivepy-0.3.1.dist-info/WHEEL
hw_hivepy-0.3.1.dist-info/top_level.txt
hw_hivepy-0.3.1.dist-info/RECORD
