Metadata-Version: 2.1
Name: hw-hivepy
Version: 0.3.1
Summary: Small wrapper for HexWay Hive API
Home-page: https://github.com/Cur1iosity/hivepy
Author: @Cur1iosity
Author-email: Cur1iosity@protonmail.com
Classifier: Programming Language :: Python :: 3
Classifier: License :: OSI Approved :: MIT License
Classifier: Operating System :: OS Independent
Requires-Python: >=3.12
Requires-Dist: requests >=2.31.0
Requires-Dist: pydantic >=2.4.0
Provides-Extra: dev
Requires-Dist: pytest ; extra == 'dev'
